{"sorts": ["object", "label"], "predicates": {"left": "(object, object)", "below": "(object, object)", "above": "(object, object)", "within": "(object, object)", "right": "(object, object)", "has_label": "(object, label)"}, "elements": {"object": ["obj_racket", "obj_ball", "obj_person"], "label": ["ball", "person", "racket"]}, "interpretation": {"left": [["obj_racket", "obj_ball"], ["obj_racket", "obj_person"], ["obj_person", "obj_ball"]], "below": [["obj_racket", "obj_ball"], ["obj_person", "obj_racket"], ["obj_person", "obj_ball"]], "above": [["obj_racket", "obj_person"], ["obj_ball", "obj_racket"], ["obj_ball", "obj_person"]], "within": [["obj_racket", "obj_person"]], "right": [["obj_ball", "obj_racket"], ["obj_ball", "obj_person"], ["obj_person", "obj_racket"]], "has_label": [["obj_racket", "racket"], ["obj_ball", "ball"], ["obj_person", "person"]]}, "raw": {"rel_labels": [["obj", "racket", "obj", "ball", "left", "0.77"], ["obj", "racket", "obj", "ball", "below", "0.77"], ["obj", "racket", "obj", "person", "left", "0.9900000000000001"], ["obj", "racket", "obj", "person", "above", "0.9900000000000001"], ["obj", "racket", "obj", "person", "within", "0.9900000000000001"], ["obj", "ball", "obj", "racket", "right", "0.77"], ["obj", "ball", "obj", "racket", "above", "0.77"], ["obj", "ball", "obj", "person", "right", "0.7623000000000001"], ["obj", "ball", "obj", "person", "above", "0.7623000000000001"], ["obj", "person", "obj", "racket", "right", "0.9900000000000001"], ["obj", "person", "obj", "racket", "below", "0.9900000000000001"], ["obj", "person", "obj", "ball", "left", "0.7623000000000001"], ["obj", "person", "obj", "ball", "below", "0.7623000000000001"]], "var_const_map": {"obj_racket": "racket", "obj_ball": "ball", "obj_person": "person"}, "scores": [["obj_racket", "obj_ball", "0.77"], ["obj_racket", "obj_ball", "0.77"], ["obj_racket", "obj_person", "0.9900000000000001"], ["obj_racket", "obj_person", "0.9900000000000001"], ["obj_racket", "obj_person", "0.9900000000000001"], ["obj_ball", "obj_racket", "0.77"], ["obj_ball", "obj_racket", "0.77"], ["obj_ball", "obj_person", "0.7623000000000001"], ["obj_ball", "obj_person", "0.7623000000000001"], ["obj_person", "obj_racket", "0.9900000000000001"], ["obj_person", "obj_racket", "0.9900000000000001"], ["obj_person", "obj_ball", "0.7623000000000001"], ["obj_person", "obj_ball", "0.7623000000000001"]]}}