{"sorts": ["object", "label"], "predicates": {"behind": "(object, object)", "watching": "(object, object)", "wearing": "(object, object)", "has_label": "(object, label)"}, "elements": {"object": ["12_hat", "10_short", "0_man", "2_man", "16_boy", "9_man", "18_tree", "4_man", "3_sock", "19_shoe", "1_man", "14_sock"], "label": ["short", "shoe", "tree", "hat", "man", "boy", "sock"]}, "interpretation": {"behind": [["18_tree", "2_man"], ["18_tree", "0_man"], ["18_tree", "1_man"], ["18_tree", "4_man"], ["18_tree", "16_boy"]], "watching": [["9_man", "2_man"], ["9_man", "4_man"]], "wearing": [["16_boy", "14_sock"], ["16_boy", "3_sock"], ["4_man", "14_sock"], ["4_man", "3_sock"], ["9_man", "3_sock"], ["2_man", "3_sock"], ["16_boy", "19_shoe"], ["16_boy", "10_short"], ["0_man", "3_sock"], ["0_man", "14_sock"], ["16_boy", "12_hat"], ["1_man", "19_shoe"], ["9_man", "10_short"]], "has_label": [["18_tree", "tree"], ["9_man", "man"], ["16_boy", "boy"], ["4_man", "man"], ["2_man", "man"], ["0_man", "man"], ["1_man", "man"], ["14_sock", "sock"], ["3_sock", "sock"], ["19_shoe", "shoe"], ["10_short", "short"], ["12_hat", "hat"]]}, "raw": {"rel_labels": [[18, "tree", 2, "man", "behind", "0.9300394654273987"], [18, "tree", 0, "man", "behind", "0.874405026435852"], [18, "tree", 1, "man", "behind", "0.821976900100708"], [18, "tree", 4, "man", "behind", "0.8091531991958618"], [9, "man", 2, "man", "watching", "0.8087416291236877"], [16, "boy", 14, "sock", "wearing", "0.7881192564964294"], [16, "boy", 3, "sock", "wearing", "0.7880343794822693"], [4, "man", 14, "sock", "wearing", "0.7779573798179626"], [4, "man", 3, "sock", "wearing", "0.7741579413414001"], [9, "man", 3, "sock", "wearing", "0.7715069055557251"], [2, "man", 3, "sock", "wearing", "0.7707095742225647"], [16, "boy", 19, "shoe", "wearing", "0.7688326835632324"], [16, "boy", 10, "short", "wearing", "0.7677115797996521"], [0, "man", 3, "sock", "wearing", "0.7674244046211243"], [0, "man", 14, "sock", "wearing", "0.7673166394233704"], [16, "boy", 12, "hat", "wearing", "0.765068769454956"], [1, "man", 19, "shoe", "wearing", "0.7648131251335144"], [18, "tree", 16, "boy", "behind", "0.7646335363388062"], [9, "man", 4, "man", "watching", "0.7644734978675842"], [9, "man", 10, "short", "wearing", "0.7639691829681396"]], "var_const_map": {"18_tree": "tree", "9_man": "man", "16_boy": "boy", "4_man": "man", "2_man": "man", "0_man": "man", "1_man": "man", "14_sock": "sock", "3_sock": "sock", "19_shoe": "shoe", "10_short": "short", "12_hat": "hat"}, "scores": [["18_tree", "2_man", "0.9300394654273987"], ["18_tree", "0_man", "0.874405026435852"], ["18_tree", "1_man", "0.821976900100708"], ["18_tree", "4_man", "0.8091531991958618"], ["9_man", "2_man", "0.8087416291236877"], ["16_boy", "14_sock", "0.7881192564964294"], ["16_boy", "3_sock", "0.7880343794822693"], ["4_man", "14_sock", "0.7779573798179626"], ["4_man", "3_sock", "0.7741579413414001"], ["9_man", "3_sock", "0.7715069055557251"], ["2_man", "3_sock", "0.7707095742225647"], ["16_boy", "19_shoe", "0.7688326835632324"], ["16_boy", "10_short", "0.7677115797996521"], ["0_man", "3_sock", "0.7674244046211243"], ["0_man", "14_sock", "0.7673166394233704"], ["16_boy", "12_hat", "0.765068769454956"], ["1_man", "19_shoe", "0.7648131251335144"], ["18_tree", "16_boy", "0.7646335363388062"], ["9_man", "4_man", "0.7644734978675842"], ["9_man", "10_short", "0.7639691829681396"]]}}