{"sorts": ["object", "label", "scores"], "predicates": {"left_below": "(object, object)", "right_above": "(object, object)", "has label": "(object, label)", "has score": "(object, object, score)"}, "elements": {"object": ["obj_person", "obj_sheep", "obj_dog"], "label": ["person", "dog", "sheep"], "scores": [0.4984, 0.89, 0.4984, 0.56, 0.89, 0.56]}, "interpretation": {"left_below": [["obj_sheep", "obj_dog"], ["obj_person", "obj_sheep"], ["obj_person", "obj_dog"]], "right_above": [["obj_sheep", "obj_person"], ["obj_dog", "obj_sheep"], ["obj_dog", "obj_person"]], "has label": [["obj_sheep", "sheep"], ["obj_dog", "dog"], ["obj_person", "person"]], "has score": [["obj_sheep", "obj_dog", 0.4984], ["obj_sheep", "obj_person", 0.89], ["obj_dog", "obj_sheep", 0.4984], ["obj_dog", "obj_person", 0.56], ["obj_person", "obj_sheep", 0.89], ["obj_person", "obj_dog", 0.56]]}, "raw": [["obj", "sheep", "obj", "dog", "left_below", 0.4984], ["obj", "sheep", "obj", "person", "right_above", 0.89], ["obj", "dog", "obj", "sheep", "right_above", 0.4984], ["obj", "dog", "obj", "person", "right_above", 0.56], ["obj", "person", "obj", "sheep", "left_below", 0.89], ["obj", "person", "obj", "dog", "left_below", 0.56]]}